aws_tgw_routes/__init__.py
aws_tgw_routes/__init__.pyi
aws_tgw_routes/__main__.py
aws_tgw_routes/__main__.pyi
aws_tgw_routes/add_tgw_routes.py
aws_tgw_routes/add_tgw_routes.pyi
aws_tgw_routes/get_tgw_routes.py
aws_tgw_routes/get_tgw_routes.pyi
aws_tgw_routes/py.typed
aws_tgw_routes-1.0.4.dist-info/METADATA
aws_tgw_routes-1.0.4.dist-info/WHEEL
aws_tgw_routes-1.0.4.dist-info/RECORD
